example_sample_lav/__init__.py
example_sample_lav/text.py
example_sample_lav-0.7.dist-info/METADATA
example_sample_lav-0.7.dist-info/RECORD
example_sample_lav-0.7.dist-info/WHEEL
example_sample_lav-0.7.dist-info/top_level.txt
