Metadata-Version: 2.1
Name: example-sample-lav
Version: 0.7
Summary: 1st prog
Home-page: https://www.python.org/lavanya123/example_sample_lav/
Author: lavanya123
Author-email: lavanyapavuluri@123.com
License: MIT
Platform: UNKNOWN
